iflow_mcp_mcp_google_contacts_server-0.1.1.dist-info/licenses/LICENSE
mcp_google_contacts_server/config.py
mcp_google_contacts_server/formatters.py
mcp_google_contacts_server/google_contacts_service.py
mcp_google_contacts_server/main.py
mcp_google_contacts_server/tools.py
iflow_mcp_mcp_google_contacts_server-0.1.1.dist-info/METADATA
iflow_mcp_mcp_google_contacts_server-0.1.1.dist-info/WHEEL
iflow_mcp_mcp_google_contacts_server-0.1.1.dist-info/entry_points.txt
iflow_mcp_mcp_google_contacts_server-0.1.1.dist-info/top_level.txt
iflow_mcp_mcp_google_contacts_server-0.1.1.dist-info/RECORD
