Metadata-Version: 2.4
Name: iflow-mcp_mcp-google-contacts-server
Version: 0.1.1
Summary: MCP server for Google Contacts integration
Home-page: https://github.com/rayanzaki/mcp-google-contacts-server
Author: Rayan Zaki
Author-email: Rayan Zaki <rayan.hassici@ensia.edu.dz>
License: MIT License
Project-URL: Homepage, https://github.com/rayanzaki/mcp-google-contacts-server
Project-URL: Bug Tracker, https://github.com/rayanzaki/mcp-google-contacts-server/issues
Classifier: Programming Language :: Python :: 3
Classifier: License :: OSI Approved :: MIT License
Classifier: Operating System :: OS Independent
Requires-Python: >=3.6
License-File: LICENSE
Requires-Dist: fastmcp
Requires-Dist: google-api-python-client
Requires-Dist: google-auth
Requires-Dist: google-auth-oauthlib
Dynamic: author
Dynamic: home-page
Dynamic: license-file
Dynamic: requires-python
